MyLib/__init__.py
MyLib/guides.py
MyLib/narek.py
mysqlLibRan-0.0.5.dist-info/METADATA
mysqlLibRan-0.0.5.dist-info/WHEEL
mysqlLibRan-0.0.5.dist-info/top_level.txt
mysqlLibRan-0.0.5.dist-info/RECORD
